diffs/__init__.py
diffs/apps.py
diffs/helpers.py
diffs/models.py
diffs/settings.py
diffs/signals.py
diffs/management/__init__.py
diffs/management/commands/__init__.py
diffs/management/commands/prune_diffs.py
django_diffs-0.1.16.dist-info/DESCRIPTION.rst
django_diffs-0.1.16.dist-info/METADATA
django_diffs-0.1.16.dist-info/RECORD
django_diffs-0.1.16.dist-info/WHEEL
django_diffs-0.1.16.dist-info/metadata.json
django_diffs-0.1.16.dist-info/top_level.txt
